{
  "brokers": [
    {
      "id": 1,
      "nombre": "DELTA DEDICATED LLC",
      "mc": "704324",
      "buyLimit": 5000
    },
    {
      "id": 2,
      "nombre": "1 SOLUTION LOGISTICS",
      "mc": "157327",
      "buyLimit": 0
    },
    {
      "id": 3,
      "nombre": "10-4 LOGISTICS LLC",
      "mc": "27505",
      "buyLimit": 15000
    },
    {
      "id": 4,
      "nombre": "1ST CHOICE FREIGHT LLC",
      "mc": "1341565",
      "buyLimit": 10000
    },
    {
      "id": 5,
      "nombre": "1ST CHOICE LOGISTICS LC",
      "mc": "586997",
      "buyLimit": 26000
    }
  ],
  "carriers": [
    {
      "id": 1,
      "nombre": "042 FREIGHT LLC",
      "buyLimit": 10000,
      "openAR": 0,
      "powerUnits": 1,
      "fechaContrato": "2024-03-11"
    },
    {
      "id": 2,
      "nombre": "1 HAUL INC",
      "buyLimit": 5000,
      "openAR": 0,
      "powerUnits": 2,
      "fechaContrato": "2021-08-27"
    },
    {
      "id": 3,
      "nombre": "1STGEN LOGISTIC LLC",
      "buyLimit": 25000,
      "openAR": 0,
      "powerUnits": 1,
      "fechaContrato": "2025-11-26"
    }
  ],
  "history": []
}
